assets/favicon.svg
docs/conf.py
jdaviz/__init__.py
jdaviz/app.py
jdaviz/app.vue
jdaviz/cli.py
jdaviz/conftest.py
jdaviz/container.vue
jdaviz/main_styles.vue
jdaviz/pytest_memlog.py
jdaviz/qt.py
jdaviz/solara.css
jdaviz/solara.py
jdaviz/style_registry.py
jdaviz/utils.py
jdaviz/version.py
jdaviz/viewer_window.vue
jdaviz/components/__init__.py
jdaviz/components/about_menu.vue
jdaviz/components/child_layer_icon.vue
jdaviz/components/custom_toolbar_toggle.vue
jdaviz/components/data_menu_add.vue
jdaviz/components/data_menu_remove.vue
jdaviz/components/data_menu_subset_edit.vue
jdaviz/components/docs_link.vue
jdaviz/components/external_link.vue
jdaviz/components/glue_state_select.vue
jdaviz/components/glue_state_sync_wrapper.vue
jdaviz/components/hover_api_hint.vue
jdaviz/components/layer_viewer_icon.vue
jdaviz/components/layer_viewer_icon_stylized.vue
jdaviz/components/loader.vue
jdaviz/components/loader_panel.vue
jdaviz/components/multiselect_toggle.vue
jdaviz/components/new_viewer_panel.vue
jdaviz/components/number_uncertainty.vue
jdaviz/components/play_pause_widget.vue
jdaviz/components/plugin_action_button.vue
jdaviz/components/plugin_add_results.vue
jdaviz/components/plugin_auto_label.vue
jdaviz/components/plugin_color_picker.vue
jdaviz/components/plugin_dataset_select.vue
jdaviz/components/plugin_editable_select.vue
jdaviz/components/plugin_file_import_select.vue
jdaviz/components/plugin_inline_select.vue
jdaviz/components/plugin_inline_select_item.vue
jdaviz/components/plugin_input_header.vue
jdaviz/components/plugin_layer_select.vue
jdaviz/components/plugin_layer_select_tabs.vue
jdaviz/components/plugin_live_results_icon.vue
jdaviz/components/plugin_loaders_panel.vue
jdaviz/components/plugin_plot.vue
jdaviz/components/plugin_popout.vue
jdaviz/components/plugin_previews_temp_disabled.vue
jdaviz/components/plugin_section_header.vue
jdaviz/components/plugin_select.vue
jdaviz/components/plugin_select_filter.vue
jdaviz/components/plugin_slider.vue
jdaviz-4.5.0.dist-info/licenses/LICENSE.rst
jdaviz-4.5.0.dist-info/licenses/licenses/GINGA_LICENSE.txt
jdaviz-4.5.0.dist-info/licenses/licenses/IMEXAM_LICENSE.txt
jdaviz-4.5.0.dist-info/licenses/licenses/IPYFILECHOOSER_LICENSE.rst
jdaviz-4.5.0.dist-info/licenses/licenses/TEMPLATE_LICENCE.rst
jdaviz-4.5.0.dist-info/METADATA
jdaviz-4.5.0.dist-info/WHEEL
jdaviz-4.5.0.dist-info/entry_points.txt
jdaviz-4.5.0.dist-info/top_level.txt
jdaviz-4.5.0.dist-info/RECORD
