Metadata-Version: 2.4
Name: jdaviz
Version: 4.5.0
Summary: Astronomical data analysis development leveraging the Jupyter platform
Author: JDADF Developers
Project-URL: Homepage, https://jdaviz.readthedocs.io/en/latest/
Requires-Python: >=3.11
License-File: LICENSE.rst
License-File: licenses/IPYFILECHOOSER_LICENSE.rst
License-File: licenses/IMEXAM_LICENSE.txt
License-File: licenses/GINGA_LICENSE.txt
License-File: licenses/TEMPLATE_LICENCE.rst
Requires-Dist: packaging
Requires-Dist: astropy>=6
Requires-Dist: matplotlib>=3.6
Requires-Dist: traitlets>=5.0.5
Requires-Dist: bqplot<0.13,>=0.12.45
Requires-Dist: glue-core>=1.23.0
Requires-Dist: glue-jupyter>=0.25.0
Requires-Dist: echo>=0.11.0
Requires-Dist: ipykernel>=6.19.4
Requires-Dist: ipyvue>=1.6
Requires-Dist: ipyvuetify<3.0,>=1.7.0
Requires-Dist: ipysplitpanes>=0.1.0
Requires-Dist: ipygoldenlayout>=0.3.0
Requires-Dist: ipywidgets>=8.0.6
Requires-Dist: solara>=1.49.0
Requires-Dist: pyyaml>=5.4.1
Requires-Dist: specutils>=2.0.0
Requires-Dist: specreduce>=1.6.0
Requires-Dist: photutils>=2.2
Requires-Dist: glue-astronomy>=0.12.0
Requires-Dist: asteval>=0.9.23
Requires-Dist: idna
Requires-Dist: vispy>=0.6.5
Requires-Dist: asdf>=2.14.3
Requires-Dist: stdatamodels>=1.3
Requires-Dist: gwcs>=0.16.1
Requires-Dist: regions>=0.6
Requires-Dist: scikit-image
Requires-Dist: sidecar>=0.5.2
Requires-Dist: ipypopout>=2.0.1
Requires-Dist: astroquery
Requires-Dist: requests
Requires-Dist: nbclassic
Requires-Dist: pyvo>=1.5.3
Requires-Dist: s3fs>=2024.10.0
Requires-Dist: joblib>=1.3.0
Requires-Dist: ipyvuedraggable>=1.1.0
Provides-Extra: all
Requires-Dist: opencv-python; extra == "all"
Requires-Dist: pysiaf; extra == "all"
Requires-Dist: strauss; extra == "all"
Requires-Dist: qtpy; extra == "all"
Requires-Dist: PySide6; extra == "all"
Requires-Dist: roman_datamodels>=0.26.0; extra == "all"
Provides-Extra: test
Requires-Dist: pytest; extra == "test"
Requires-Dist: pytest-astropy; extra == "test"
Requires-Dist: pytest-tornasync; extra == "test"
Provides-Extra: docs
Requires-Dist: sphinx-astropy[confv2]>=1.9.1; extra == "docs"
Requires-Dist: sphinx_design; extra == "docs"
Provides-Extra: roman
Requires-Dist: roman_datamodels>=0.26.0; extra == "roman"
Provides-Extra: strauss
Requires-Dist: strauss; extra == "strauss"
Provides-Extra: qt
Requires-Dist: qtpy; extra == "qt"
Requires-Dist: PySide6; extra == "qt"
Dynamic: license-file
